second_brain_database/__init__.py
second_brain_database/config.py
second_brain_database/database.py
second_brain_database/main.py
second_brain_database/admin/__init__.py
second_brain_database/admin/v1/plans/__init__.py
second_brain_database/admin/v1/plans/model.py
second_brain_database/admin/v1/plans/routes.py
second_brain_database/auth/__init__.py
second_brain_database/auth/model.py
second_brain_database/auth/routes.py
second_brain_database/auth/services.py
second_brain_database/user/__init__.py
second_brain_database/user/v1/__init__.py
second_brain_database/user/v1/emotion_tracker/__init__.py
second_brain_database/user/v1/emotion_tracker/model.py
second_brain_database/user/v1/emotion_tracker/routes.py
second_brain_database/user/v1/notes/__init__.py
second_brain_database/user/v1/notes/model.py
second_brain_database/user/v1/notes/routes.py
second_brain_database/utils/decorators/privileged.py
second_brain_database-0.0.5.dist-info/METADATA
second_brain_database-0.0.5.dist-info/WHEEL
second_brain_database-0.0.5.dist-info/top_level.txt
second_brain_database-0.0.5.dist-info/RECORD
