Metadata-Version: 2.4
Name: second_brain_database
Version: 0.0.5
Summary: A Python package that serves as the foundation for my Second Brain database, designed to store and organize knowledge for easy retrieval through various applications.
Author-email: Rohan Batra <contact@rohanbatra.in>
Project-URL: Homepage, https://github.com/rohanbatrain/second-brain-database
Project-URL: Bug Tracker, https://github.com/rohanbatrain/second-brain-database/issues
Classifier: Programming Language :: Python :: 3
Classifier: License :: OSI Approved :: MIT License
Classifier: Operating System :: OS Independent
Requires-Python: >=3.7
Requires-Dist: flask
Requires-Dist: pymongo
Requires-Dist: flask-cors
Requires-Dist: PyJWT
Requires-Dist: bcrypt
Requires-Dist: gunicorn
Requires-Dist: flask-limiter
Requires-Dist: redis
Requires-Dist: flask_mail
Requires-Dist: mailtrap
Requires-Dist: python-dotenv
